scrapping/__init__.py
scrapping/data_handler.py
scrapping/requests.py
scrapping/spider.py
scrapping/spiders.py
tests/__init__.py
tests/requests_test.py
tests/spider_test.py
scrapping-0.1.dev0.dist-info/LICENSE
scrapping-0.1.dev0.dist-info/METADATA
scrapping-0.1.dev0.dist-info/WHEEL
scrapping-0.1.dev0.dist-info/top_level.txt
scrapping-0.1.dev0.dist-info/RECORD
